confypy/__init__.py
confypy/compat.py
confypy/confypy.py
confypy/exceptions.py
confypy/loaders.py
confypy/parsers.py
confypy-0.2.5.dist-info/DESCRIPTION.rst
confypy-0.2.5.dist-info/METADATA
confypy-0.2.5.dist-info/metadata.json
confypy-0.2.5.dist-info/RECORD
confypy-0.2.5.dist-info/top_level.txt
confypy-0.2.5.dist-info/WHEEL
